ratio_case-0.1.0.dist-info/METADATA
ratio_case-0.1.0.dist-info/WHEEL
ratio_case/__init__.py
ratio_case/__init__.pyi
ratio_case/__pycache__/__init__.cpython-311.pyc
ratio_case/__pycache__/__init__.cpython-313.pyc
ratio_case/py.typed
ratio_case/ratio_case.abi3.so
ratio_case-0.1.0.dist-info/RECORD
