Metadata-Version: 2.4
Name: ratio-case
Version: 0.1.0
Classifier: Programming Language :: Rust
Classifier: Programming Language :: Python :: Implementation :: CPython
Classifier: Programming Language :: Python :: Implementation :: PyPy
Classifier: License :: OSI Approved :: Mozilla Public License 2.0 (MPL 2.0)
Classifier: Topic :: Scientific/Engineering :: Mathematics
Classifier: Topic :: Software Development :: Libraries
Classifier: Development Status :: 3 - Alpha
Summary: Python bindings for Ratio's CASE crate collection.
Keywords: case,systems engineering,graph,algorithms,genetic,mathematics,sga,clustering,sequencing,rust
Home-Page: https://gitlab.com/ratio-case-os/rust/ratio-case/-/tree/main/python
Author-email: "Ratio Innovations B.V." <info@ratio-case.nl>
License: MPL-2.0
Requires-Python: >=3.11
Project-URL: Source Code, https://gitlab.com/ratio-case-os/rust/ratio-case.git
